{"assets":[{"id":"comp_5","layers":[{"ddd":0,"ind":0,"ty":4,"nm":"pie_stroke_center_ball","ks":{"o":{"k":100},"r":{"k":0},"p":{"k":[512,512,0]},"a":{"k":[0,0,0]},"s":{"k":[{"i":{"x":[0.667,0.667,0.667],"y":[1,1,0.667]},"o":{"x":[0.333,0.333,0.333],"y":[0,0,0.333]},"n":["0p667_1_0p333_0","0p667_1_0p333_0","0p667_0p667_0p333_0p333"],"t":22,"s":[0,0,100],"e":[100,100,100]},{"t":25.0000010182709}]}},"ao":0,"shapes":[{"d":1,"ty":"el","s":{"k":[20,20]},"p":{"k":[0,0]},"nm":"Ellipse Path 1","mn":"ADBE Vector Shape - Ellipse"},{"ty":"tm","s":{"k":0,"ix":1},"e":{"k":100,"ix":2},"o":{"k":0,"ix":3},"m":1,"ix":2,"nm":"Trim Paths 1","mn":"ADBE Vector Filter - Trim"},{"ty":"fl","c":{"k":[0.17,0.99,0.96,1]},"o":{"k":100},"nm":"Fill 1","mn":"ADBE Vector Graphic - Fill"},{"ty":"st","c":{"k":[0,1,0.97,1]},"o":{"k":100},"w":{"k":10},"lc":1,"lj":1,"ml":1,"nm":"Stroke 1","mn":"ADBE Vector Graphic - Stroke"}],"ip":22.0000008960784,"op":147.000005987433,"st":22.0000008960784,"bm":0,"sr":1},{"ddd":0,"ind":1,"ty":4,"nm":"pie_stroke_rear","ks":{"o":{"k":100},"r":{"k":0},"p":{"k":[512,512,0]},"a":{"k":[0,0,0]},"s":{"k":[100,100,100]}},"ao":0,"shapes":[{"ty":"gr","it":[{"ind":0,"ty":"sh","ks":{"k":[{"i":{"x":0.667,"y":1},"o":{"x":0.333,"y":0},"n":"0p667_1_0p333_0","t":28,"s":[{"i":[[0,0],[0,0]],"o":[[0,0],[0,0]],"v":[[-2,2],[6.182,-2.298]],"c":false}],"e":[{"i":[[0,0],[0,0]],"o":[[0,0],[0,0]],"v":[[-2,2],[-1.968,-228]],"c":false}]},{"i":{"x":0.833,"y":1},"o":{"x":0.167,"y":0},"n":"0p833_1_0p167_0","t":36.571,"s":[{"i":[[0,0],[0,0]],"o":[[0,0],[0,0]],"v":[[-2,2],[-1.968,-228]],"c":false}],"e":[{"i":[[0,0],[0,0]],"o":[[0,0],[0,0]],"v":[[-2,2],[-1.968,-228]],"c":false}]},{"i":{"x":0.833,"y":1},"o":{"x":0.167,"y":0},"n":"0p833_1_0p167_0","t":72,"s":[{"i":[[0,0],[0,0]],"o":[[0,0],[0,0]],"v":[[-2,2],[-1.968,-228]],"c":false}],"e":[{"i":[[0,0],[0,0]],"o":[[0,0],[0,0]],"v":[[-2,2],[-1.967,-294.75]],"c":false}]},{"t":73.000002973351}]},"nm":"Path 1","mn":"ADBE Vector Shape - Group"},{"ty":"st","c":{"k":[0,1,0.97,1]},"o":{"k":100},"w":{"k":20},"lc":1,"lj":1,"ml":4,"nm":"Stroke 1","mn":"ADBE Vector Graphic - Stroke"},{"ty":"tr","p":{"k":[0,0],"ix":2},"a":{"k":[0,0],"ix":1},"s":{"k":[100,100],"ix":3},"r":{"k":[{"i":{"x":[0.667],"y":[1]},"o":{"x":[0.515],"y":[0]},"n":["0p667_1_0p515_0"],"t":28,"s":[385],"e":[360]},{"t":79.000003217736}],"ix":6},"o":{"k":100,"ix":7},"sk":{"k":0,"ix":4},"sa":{"k":0,"ix":5},"nm":"Transform"}],"nm":"Shape 1","np":2,"mn":"ADBE Vector Group"}],"ip":28.0000011404634,"op":147.000005987433,"st":28.0000011404634,"bm":0,"sr":1},{"ddd":0,"ind":2,"ty":4,"nm":"pie_stroke_front","ks":{"o":{"k":100},"r":{"k":0},"p":{"k":[512,512,0]},"a":{"k":[0,0,0]},"s":{"k":[100,100,100]}},"ao":0,"shapes":[{"ty":"gr","it":[{"ind":0,"ty":"sh","ks":{"k":[{"i":{"x":0.667,"y":1},"o":{"x":0.333,"y":0},"n":"0p667_1_0p333_0","t":31.429,"s":[{"i":[[0,0],[0,0]],"o":[[0,0],[0,0]],"v":[[-2,2],[-4.127,-5.421]],"c":false}],"e":[{"i":[[0,0],[0,0]],"o":[[0,0],[0,0]],"v":[[-2,2],[-2,-292]],"c":false}]},{"t":40.0000016292334}]},"nm":"Path 1","mn":"ADBE Vector Shape - Group"},{"ty":"st","c":{"k":[0,1,0.97,1]},"o":{"k":100},"w":{"k":20},"lc":1,"lj":1,"ml":4,"nm":"Stroke 1","mn":"ADBE Vector Graphic - Stroke"},{"ty":"tr","p":{"k":[0,0],"ix":2},"a":{"k":[0,0],"ix":1},"s":{"k":[100,100],"ix":3},"r":{"k":[{"i":{"x":[0.52],"y":[1]},"o":{"x":[0.515],"y":[0]},"n":["0p52_1_0p515_0"],"t":20,"s":[360],"e":[-157]},{"t":105.000004276738}],"ix":6},"o":{"k":100,"ix":7},"sk":{"k":0,"ix":4},"sa":{"k":0,"ix":5},"nm":"Transform"}],"nm":"Shape 1","np":2,"mn":"ADBE Vector Group"}],"ip":28.0000011404634,"op":147.000005987433,"st":28.0000011404634,"bm":0,"sr":1},{"ddd":0,"ind":3,"ty":4,"nm":"pie_stroke_arc","ks":{"o":{"k":100},"r":{"k":0},"p":{"k":[512,512,0]},"a":{"k":[0,0,0]},"s":{"k":[100,100,100]}},"ao":0,"shapes":[{"d":1,"ty":"el","s":{"k":[570,570]},"p":{"k":[0,0]},"nm":"Ellipse Path 1","mn":"ADBE Vector Shape - Ellipse"},{"ty":"tm","s":{"k":[{"i":{"x":[0.833],"y":[0.833]},"o":{"x":[0.167],"y":[0.167]},"n":["0p833_0p833_0p167_0p167"],"t":72,"s":[100],"e":[94.43]},{"i":{"x":[0.833],"y":[0.833]},"o":{"x":[0.167],"y":[0.167]},"n":["0p833_0p833_0p167_0p167"],"t":74,"s":[94.43],"e":[89.259]},{"i":{"x":[0.833],"y":[0.833]},"o":{"x":[0.167],"y":[0.167]},"n":["0p833_0p833_0p167_0p167"],"t":76,"s":[89.259],"e":[86.556]},{"i":{"x":[0.833],"y":[0.833]},"o":{"x":[0.167],"y":[0.167]},"n":["0p833_0p833_0p167_0p167"],"t":77,"s":[86.556],"e":[81.75]},{"i":{"x":[0.833],"y":[0.833]},"o":{"x":[0.167],"y":[0.167]},"n":["0p833_0p833_0p167_0p167"],"t":79,"s":[81.75],"e":[77.41]},{"i":{"x":[0.833],"y":[0.833]},"o":{"x":[0.167],"y":[0.167]},"n":["0p833_0p833_0p167_0p167"],"t":81,"s":[77.41],"e":[75.4]},{"i":{"x":[0.833],"y":[0.833]},"o":{"x":[0.167],"y":[0.167]},"n":["0p833_0p833_0p167_0p167"],"t":82,"s":[75.4],"e":[70.151]},{"i":{"x":[0.833],"y":[0.833]},"o":{"x":[0.167],"y":[0.167]},"n":["0p833_0p833_0p167_0p167"],"t":85,"s":[70.151],"e":[67.151]},{"i":{"x":[0.833],"y":[0.833]},"o":{"x":[0.167],"y":[0.167]},"n":["0p833_0p833_0p167_0p167"],"t":87,"s":[67.151],"e":[64.519]},{"i":{"x":[0.833],"y":[0.833]},"o":{"x":[0.167],"y":[0.167]},"n":["0p833_0p833_0p167_0p167"],"t":89,"s":[64.519],"e":[63.352]},{"i":{"x":[0.833],"y":[0.833]},"o":{"x":[0.167],"y":[0.167]},"n":["0p833_0p833_0p167_0p167"],"t":90,"s":[63.352],"e":[61.32]},{"i":{"x":[0.833],"y":[0.833]},"o":{"x":[0.167],"y":[0.167]},"n":["0p833_0p833_0p167_0p167"],"t":92,"s":[61.32],"e":[59.689]},{"i":{"x":[0.833],"y":[0.833]},"o":{"x":[0.167],"y":[0.167]},"n":["0p833_0p833_0p167_0p167"],"t":94,"s":[59.689],"e":[58.973]},{"i":{"x":[0.833],"y":[0.833]},"o":{"x":[0.167],"y":[0.167]},"n":["0p833_0p833_0p167_0p167"],"t":95,"s":[58.973],"e":[58.257]},{"i":{"x":[0.833],"y":[0.833]},"o":{"x":[0.167],"y":[0.167]},"n":["0p833_0p833_0p167_0p167"],"t":96,"s":[58.257],"e":[57.212]},{"i":{"x":[0.833],"y":[0.833]},"o":{"x":[0.167],"y":[0.167]},"n":["0p833_0p833_0p167_0p167"],"t":98,"s":[57.212],"e":[56.84]},{"i":{"x":[0.833],"y":[0.833]},"o":{"x":[0.167],"y":[0.167]},"n":["0p833_0p833_0p167_0p167"],"t":99,"s":[56.84],"e":[56.229]},{"i":{"x":[0.833],"y":[0.833]},"o":{"x":[0.167],"y":[0.167]},"n":["0p833_0p833_0p167_0p167"],"t":101,"s":[56.229],"e":[55.963]},{"i":{"x":[0.833],"y":[0.833]},"o":{"x":[0.167],"y":[0.167]},"n":["0p833_0p833_0p167_0p167"],"t":102,"s":[55.963],"e":[55.732]},{"i":{"x":[0.833],"y":[0.833]},"o":{"x":[0.167],"y":[0.167]},"n":["0p833_0p833_0p167_0p167"],"t":104,"s":[55.732],"e":[55.7]},{"t":105.000004276738}],"ix":1},"e":{"k":100,"ix":2},"o":{"k":0,"ix":3},"m":1,"ix":2,"nm":"Trim Paths 1","mn":"ADBE Vector Filter - Trim"},{"ty":"st","c":{"k":[0,1,0.97,1]},"o":{"k":100},"w":{"k":20},"lc":1,"lj":1,"ml":1,"nm":"Stroke 1","mn":"ADBE Vector Graphic - Stroke"}],"ip":28.0000011404634,"op":147.000005987433,"st":28.0000011404634,"bm":0,"sr":1},{"ddd":0,"ind":4,"ty":0,"nm":"stripes","refId":"comp_6","ks":{"o":{"k":30},"r":{"k":0},"p":{"k":[512,512,0]},"a":{"k":[512,512,0]},"s":{"k":[100,100,100]}},"ao":0,"w":1024,"h":1024,"ip":92.0000037472368,"op":147.000005987433,"st":92.0000037472368,"bm":0,"sr":1.25},{"ddd":0,"ind":5,"ty":4,"nm":"pie_fill","ks":{"o":{"k":100},"r":{"k":0},"p":{"k":[512,512,0]},"a":{"k":[0,0,0]},"s":{"k":[100,100,100]}},"ao":0,"shapes":[{"d":1,"ty":"el","s":{"k":[285,285]},"p":{"k":[0,0]},"nm":"Ellipse Path 1","mn":"ADBE Vector Shape - Ellipse"},{"ty":"tm","s":{"k":[{"i":{"x":[0.833],"y":[0.833]},"o":{"x":[0.167],"y":[0.167]},"n":["0p833_0p833_0p167_0p167"],"t":72,"s":[100],"e":[94.43]},{"i":{"x":[0.833],"y":[0.833]},"o":{"x":[0.167],"y":[0.167]},"n":["0p833_0p833_0p167_0p167"],"t":74,"s":[94.43],"e":[89.259]},{"i":{"x":[0.833],"y":[0.833]},"o":{"x":[0.167],"y":[0.167]},"n":["0p833_0p833_0p167_0p167"],"t":76,"s":[89.259],"e":[86.556]},{"i":{"x":[0.833],"y":[0.833]},"o":{"x":[0.167],"y":[0.167]},"n":["0p833_0p833_0p167_0p167"],"t":77,"s":[86.556],"e":[81.75]},{"i":{"x":[0.833],"y":[0.833]},"o":{"x":[0.167],"y":[0.167]},"n":["0p833_0p833_0p167_0p167"],"t":79,"s":[81.75],"e":[77.41]},{"i":{"x":[0.833],"y":[0.833]},"o":{"x":[0.167],"y":[0.167]},"n":["0p833_0p833_0p167_0p167"],"t":81,"s":[77.41],"e":[75.4]},{"i":{"x":[0.833],"y":[0.833]},"o":{"x":[0.167],"y":[0.167]},"n":["0p833_0p833_0p167_0p167"],"t":82,"s":[75.4],"e":[70.151]},{"i":{"x":[0.833],"y":[0.833]},"o":{"x":[0.167],"y":[0.167]},"n":["0p833_0p833_0p167_0p167"],"t":85,"s":[70.151],"e":[67.151]},{"i":{"x":[0.833],"y":[0.833]},"o":{"x":[0.167],"y":[0.167]},"n":["0p833_0p833_0p167_0p167"],"t":87,"s":[67.151],"e":[64.519]},{"i":{"x":[0.833],"y":[0.833]},"o":{"x":[0.167],"y":[0.167]},"n":["0p833_0p833_0p167_0p167"],"t":89,"s":[64.519],"e":[63.352]},{"i":{"x":[0.833],"y":[0.833]},"o":{"x":[0.167],"y":[0.167]},"n":["0p833_0p833_0p167_0p167"],"t":90,"s":[63.352],"e":[61.32]},{"i":{"x":[0.833],"y":[0.833]},"o":{"x":[0.167],"y":[0.167]},"n":["0p833_0p833_0p167_0p167"],"t":92,"s":[61.32],"e":[59.689]},{"i":{"x":[0.833],"y":[0.833]},"o":{"x":[0.167],"y":[0.167]},"n":["0p833_0p833_0p167_0p167"],"t":94,"s":[59.689],"e":[58.973]},{"i":{"x":[0.833],"y":[0.833]},"o":{"x":[0.167],"y":[0.167]},"n":["0p833_0p833_0p167_0p167"],"t":95,"s":[58.973],"e":[58.257]},{"i":{"x":[0.833],"y":[0.833]},"o":{"x":[0.167],"y":[0.167]},"n":["0p833_0p833_0p167_0p167"],"t":96,"s":[58.257],"e":[57.212]},{"i":{"x":[0.833],"y":[0.833]},"o":{"x":[0.167],"y":[0.167]},"n":["0p833_0p833_0p167_0p167"],"t":98,"s":[57.212],"e":[56.84]},{"i":{"x":[0.833],"y":[0.833]},"o":{"x":[0.167],"y":[0.167]},"n":["0p833_0p833_0p167_0p167"],"t":99,"s":[56.84],"e":[56.229]},{"i":{"x":[0.833],"y":[0.833]},"o":{"x":[0.167],"y":[0.167]},"n":["0p833_0p833_0p167_0p167"],"t":101,"s":[56.229],"e":[55.963]},{"i":{"x":[0.833],"y":[0.833]},"o":{"x":[0.167],"y":[0.167]},"n":["0p833_0p833_0p167_0p167"],"t":102,"s":[55.963],"e":[55.732]},{"i":{"x":[0.833],"y":[0.833]},"o":{"x":[0.167],"y":[0.167]},"n":["0p833_0p833_0p167_0p167"],"t":104,"s":[55.732],"e":[55.7]},{"t":105.000004276738}],"ix":1},"e":{"k":100,"ix":2},"o":{"k":0,"ix":3},"m":1,"ix":2,"nm":"Trim Paths 1","mn":"ADBE Vector Filter - Trim"},{"ty":"st","c":{"k":[0,0.5,0.55,1]},"o":{"k":100},"w":{"k":285},"lc":1,"lj":1,"ml":1,"nm":"Stroke 1","mn":"ADBE Vector Graphic - Stroke"}],"ip":28.0000011404634,"op":147.000005987433,"st":28.0000011404634,"bm":0,"sr":1},{"ddd":0,"ind":6,"ty":4,"nm":"orange_dot","ks":{"o":{"k":[{"i":{"x":[0.833],"y":[0.833]},"o":{"x":[0.167],"y":[0.167]},"n":["0p833_0p833_0p167_0p167"],"t":25,"s":[0],"e":[100]},{"t":29.0000011811942}]},"r":{"k":[{"i":{"x":[0.52],"y":[1]},"o":{"x":[0.515],"y":[0]},"n":["0p52_1_0p515_0"],"t":20,"s":[157],"e":[-360]},{"t":105.000004276738}]},"p":{"k":[512,512,0]},"a":{"k":[50.5,50.5,0]},"s":{"k":[795,795,100]}},"ao":0,"shapes":[{"ty":"gr","it":[{"ind":0,"ty":"sh","ks":{"k":{"i":[[0,1.712],[1.712,0],[0,-1.712],[-1.713,0]],"o":[[0,-1.712],[-1.713,0],[0,1.712],[1.712,0]],"v":[[3.1,-0.001],[0.001,-3.101],[-3.1,-0.001],[0.001,3.101]],"c":true}},"nm":"Path 1","mn":"ADBE Vector Shape - Group"},{"ty":"fl","c":{"k":[0.96,0.41,0.18,1]},"o":{"k":100},"nm":"Fill 1","mn":"ADBE Vector Graphic - Fill"},{"ty":"tr","p":{"k":[31.198,96.003],"ix":2},"a":{"k":[0,0],"ix":1},"s":{"k":[100,100],"ix":3},"r":{"k":0,"ix":6},"o":{"k":100,"ix":7},"sk":{"k":0,"ix":4},"sa":{"k":0,"ix":5},"nm":"Transform"}],"nm":"orange_dot","np":2,"mn":"ADBE Vector Group"}],"ip":20.0000008146167,"op":147.000005987433,"st":20.0000008146167,"bm":0,"sr":1},{"ddd":0,"ind":7,"ty":4,"nm":"orange_stroke 2","ks":{"o":{"k":100},"r":{"k":0},"p":{"k":[566,563,0]},"a":{"k":[50.5,50.5,0]},"s":{"k":[100,100,100]}},"ao":0,"shapes":[{"ty":"gr","it":[{"d":1,"ty":"el","s":{"k":[789,789]},"p":{"k":[0,0]},"nm":"Ellipse Path 1","mn":"ADBE Vector Shape - Ellipse"},{"ty":"tm","s":{"k":[{"i":{"x":[0.833],"y":[0.833]},"o":{"x":[0.167],"y":[0.167]},"n":["0p833_0p833_0p167_0p167"],"t":72,"s":[100],"e":[94.43]},{"i":{"x":[0.833],"y":[0.833]},"o":{"x":[0.167],"y":[0.167]},"n":["0p833_0p833_0p167_0p167"],"t":74,"s":[94.43],"e":[89.259]},{"i":{"x":[0.833],"y":[0.833]},"o":{"x":[0.167],"y":[0.167]},"n":["0p833_0p833_0p167_0p167"],"t":76,"s":[89.259],"e":[86.556]},{"i":{"x":[0.833],"y":[0.833]},"o":{"x":[0.167],"y":[0.167]},"n":["0p833_0p833_0p167_0p167"],"t":77,"s":[86.556],"e":[81.75]},{"i":{"x":[0.833],"y":[0.833]},"o":{"x":[0.167],"y":[0.167]},"n":["0p833_0p833_0p167_0p167"],"t":79,"s":[81.75],"e":[77.41]},{"i":{"x":[0.833],"y":[0.833]},"o":{"x":[0.167],"y":[0.167]},"n":["0p833_0p833_0p167_0p167"],"t":81,"s":[77.41],"e":[75.4]},{"i":{"x":[0.833],"y":[0.833]},"o":{"x":[0.167],"y":[0.167]},"n":["0p833_0p833_0p167_0p167"],"t":82,"s":[75.4],"e":[70.151]},{"i":{"x":[0.833],"y":[0.833]},"o":{"x":[0.167],"y":[0.167]},"n":["0p833_0p833_0p167_0p167"],"t":85,"s":[70.151],"e":[67.151]},{"i":{"x":[0.833],"y":[0.833]},"o":{"x":[0.167],"y":[0.167]},"n":["0p833_0p833_0p167_0p167"],"t":87,"s":[67.151],"e":[64.519]},{"i":{"x":[0.833],"y":[0.833]},"o":{"x":[0.167],"y":[0.167]},"n":["0p833_0p833_0p167_0p167"],"t":89,"s":[64.519],"e":[63.352]},{"i":{"x":[0.833],"y":[0.833]},"o":{"x":[0.167],"y":[0.167]},"n":["0p833_0p833_0p167_0p167"],"t":90,"s":[63.352],"e":[61.32]},{"i":{"x":[0.833],"y":[0.833]},"o":{"x":[0.167],"y":[0.167]},"n":["0p833_0p833_0p167_0p167"],"t":92,"s":[61.32],"e":[59.689]},{"i":{"x":[0.833],"y":[0.833]},"o":{"x":[0.167],"y":[0.167]},"n":["0p833_0p833_0p167_0p167"],"t":94,"s":[59.689],"e":[58.973]},{"i":{"x":[0.833],"y":[0.833]},"o":{"x":[0.167],"y":[0.167]},"n":["0p833_0p833_0p167_0p167"],"t":95,"s":[58.973],"e":[58.257]},{"i":{"x":[0.833],"y":[0.833]},"o":{"x":[0.167],"y":[0.167]},"n":["0p833_0p833_0p167_0p167"],"t":96,"s":[58.257],"e":[57.212]},{"i":{"x":[0.833],"y":[0.833]},"o":{"x":[0.167],"y":[0.167]},"n":["0p833_0p833_0p167_0p167"],"t":98,"s":[57.212],"e":[56.84]},{"i":{"x":[0.833],"y":[0.833]},"o":{"x":[0.167],"y":[0.167]},"n":["0p833_0p833_0p167_0p167"],"t":99,"s":[56.84],"e":[56.229]},{"i":{"x":[0.833],"y":[0.833]},"o":{"x":[0.167],"y":[0.167]},"n":["0p833_0p833_0p167_0p167"],"t":101,"s":[56.229],"e":[55.963]},{"i":{"x":[0.833],"y":[0.833]},"o":{"x":[0.167],"y":[0.167]},"n":["0p833_0p833_0p167_0p167"],"t":102,"s":[55.963],"e":[55.732]},{"i":{"x":[0.833],"y":[0.833]},"o":{"x":[0.167],"y":[0.167]},"n":["0p833_0p833_0p167_0p167"],"t":104,"s":[55.732],"e":[55.7]},{"t":105.000004276738}],"ix":1},"e":{"k":100,"ix":2},"o":{"k":0,"ix":3},"m":1,"ix":2,"nm":"Trim Paths 1","mn":"ADBE Vector Filter - Trim"},{"ty":"st","c":{"k":[0.96,0.41,0.22,1]},"o":{"k":100},"w":{"k":18},"lc":1,"lj":1,"ml":1,"nm":"Stroke 1","mn":"ADBE Vector Graphic - Stroke"},{"ty":"tr","p":{"k":[0,0],"ix":2},"a":{"k":[0,0],"ix":1},"s":{"k":[100,100],"ix":3},"r":{"k":0,"ix":6},"o":{"k":100,"ix":7},"sk":{"k":0,"ix":4},"sa":{"k":0,"ix":5},"nm":"Transform"}],"nm":"orange_stroke","np":3,"mn":"ADBE Vector Group"}],"ip":28.0000011404634,"op":147.000005987433,"st":28.0000011404634,"bm":0,"sr":1},{"ddd":0,"ind":8,"ty":4,"nm":"bg","ks":{"o":{"k":100},"r":{"k":0},"p":{"k":[566,563,0]},"a":{"k":[50.5,50.5,0]},"s":{"k":[100,100,100]}},"ao":0,"shapes":[{"ty":"gr","it":[{"d":1,"ty":"el","s":{"k":[789,789]},"p":{"k":[0,0]},"nm":"Ellipse Path 1","mn":"ADBE Vector Shape - Ellipse"},{"ty":"st","c":{"k":[0.82,0.84,0.87,1]},"o":{"k":100},"w":{"k":18},"lc":1,"lj":1,"ml":1,"nm":"Stroke 1","mn":"ADBE Vector Graphic - Stroke"},{"ty":"tr","p":{"k":[0,0],"ix":2},"a":{"k":[0,0],"ix":1},"s":{"k":[100,100],"ix":3},"r":{"k":0,"ix":6},"o":{"k":100,"ix":7},"sk":{"k":0,"ix":4},"sa":{"k":0,"ix":5},"nm":"Transform"}],"nm":"strokeee","np":2,"mn":"ADBE Vector Group"}],"ip":0,"op":147.000005987433,"st":28.0000011404634,"bm":0,"sr":1},{"ddd":0,"ind":9,"ty":4,"nm":"clock_ticks","ks":{"o":{"k":100},"r":{"k":0},"p":{"k":[512,512,0]},"a":{"k":[50.5,50.5,0]},"s":{"k":[795,795,100]}},"ao":0,"shapes":[{"ty":"gr","it":[{"ind":0,"ty":"sh","ks":{"k":[{"i":{"x":0.667,"y":1},"o":{"x":0.333,"y":0},"n":"0p667_1_0p333_0","t":17,"s":[{"i":[[0,0],[0,0],[0,0],[0,0]],"o":[[0,0],[0,0],[0,0],[0,0]],"v":[[1,-1.924],[-1,-1.924],[-1,-2.794],[1,-2.794]],"c":true}],"e":[{"i":[[0,0],[0,0],[0,0],[0,0]],"o":[[0,0],[0,0],[0,0],[0,0]],"v":[[1,2.794],[-1,2.794],[-1,-2.794],[1,-2.794]],"c":true}]},{"t":21.0000008553475}]},"nm":"Path 1","mn":"ADBE Vector Shape - Group"},{"ty":"tr","p":{"k":[50.444,3.793],"ix":2},"a":{"k":[0,0],"ix":1},"s":{"k":[100,100],"ix":3},"r":{"k":0,"ix":6},"o":{"k":100,"ix":7},"sk":{"k":0,"ix":4},"sa":{"k":0,"ix":5},"nm":"Transform"}],"nm":"12","np":1,"mn":"ADBE Vector Group"},{"ty":"gr","it":[{"ind":0,"ty":"sh","ks":{"k":[{"i":{"x":0.667,"y":1},"o":{"x":0.333,"y":0},"n":"0p667_1_0p333_0","t":19,"s":[{"i":[[0,0],[0,0],[0,0],[0,0]],"o":[[0,0],[0,0],[0,0],[0,0]],"v":[[-2.112,1],[-2.794,1],[-2.794,-1],[-2.112,-1]],"c":true}],"e":[{"i":[[0,0],[0,0],[0,0],[0,0]],"o":[[0,0],[0,0],[0,0],[0,0]],"v":[[2.794,1],[-2.794,1],[-2.794,-1],[2.794,-1]],"c":true}]},{"t":23.0000009368092}]},"nm":"Path 1","mn":"ADBE Vector Shape - Group"},{"ty":"tr","p":{"k":[3.793,50.445],"ix":2},"a":{"k":[0,0],"ix":1},"s":{"k":[100,100],"ix":3},"r":{"k":0,"ix":6},"o":{"k":100,"ix":7},"sk":{"k":0,"ix":4},"sa":{"k":0,"ix":5},"nm":"Transform"}],"nm":"9","np":1,"mn":"ADBE Vector Group"},{"ty":"gr","it":[{"ind":0,"ty":"sh","ks":{"k":[{"i":{"x":0.667,"y":1},"o":{"x":0.333,"y":0},"n":"0p667_1_0p333_0","t":21,"s":[{"i":[[0,0],[0,0],[0,0],[0,0]],"o":[[0,0],[0,0],[0,0],[0,0]],"v":[[1,2.794],[-1,2.794],[-1,2.237],[1,2.237]],"c":true}],"e":[{"i":[[0,0],[0,0],[0,0],[0,0]],"o":[[0,0],[0,0],[0,0],[0,0]],"v":[[1,2.794],[-1,2.794],[-1,-2.794],[1,-2.794]],"c":true}]},{"t":25.0000010182709}]},"nm":"Path 1","mn":"ADBE Vector Shape - Group"},{"ty":"tr","p":{"k":[50.444,97.094],"ix":2},"a":{"k":[0,0],"ix":1},"s":{"k":[100,100],"ix":3},"r":{"k":0,"ix":6},"o":{"k":100,"ix":7},"sk":{"k":0,"ix":4},"sa":{"k":0,"ix":5},"nm":"Transform"}],"nm":"6","np":1,"mn":"ADBE Vector Group"},{"ty":"gr","it":[{"ind":0,"ty":"sh","ks":{"k":[{"i":{"x":0.667,"y":1},"o":{"x":0.333,"y":0},"n":"0p667_1_0p333_0","t":23,"s":[{"i":[[0,0],[0,0],[0,0],[0,0]],"o":[[0,0],[0,0],[0,0],[0,0]],"v":[[2.794,1],[2.112,1],[2.112,-1],[2.794,-1]],"c":true}],"e":[{"i":[[0,0],[0,0],[0,0],[0,0]],"o":[[0,0],[0,0],[0,0],[0,0]],"v":[[2.794,1],[-2.794,1],[-2.794,-1],[2.794,-1]],"c":true}]},{"t":27.0000010997325}]},"nm":"Path 1","mn":"ADBE Vector Shape - Group"},{"ty":"tr","p":{"k":[97.094,50.445],"ix":2},"a":{"k":[0,0],"ix":1},"s":{"k":[100,100],"ix":3},"r":{"k":0,"ix":6},"o":{"k":100,"ix":7},"sk":{"k":0,"ix":4},"sa":{"k":0,"ix":5},"nm":"Transform"}],"nm":"3","np":1,"mn":"ADBE Vector Group"},{"ty":"mm","mm":2,"nm":"Merge Paths 1","mn":"ADBE Vector Filter - Merge"},{"ty":"fl","c":{"k":[0.82,0.84,0.88,1]},"o":{"k":100},"nm":"Fill 1","mn":"ADBE Vector Graphic - Fill"}],"ip":16.0000006516934,"op":147.000005987433,"st":24.00000097754,"bm":0,"sr":1}]},{"id":"comp_6","layers":[{"ddd":0,"ind":0,"ty":0,"nm":"stripes_spin","refId":"comp_7","ks":{"o":{"k":100},"r":{"k":0},"p":{"k":[512,512,0]},"a":{"k":[512,512,0]},"s":{"k":[100,100,100]}},"ao":0,"hasMask":true,"masksProperties":[{"inv":false,"mode":"a","pt":{"k":[{"i":{"x":0.833,"y":0.833},"o":{"x":0.167,"y":0.167},"n":"0p833_0p833_0p167_0p167","t":0,"s":[{"i":[[0,0],[0,0],[0,0],[0,0],[0,0],[0,0],[0,0],[0,0]],"o":[[0,0],[0,0],[0,0],[0,0],[0,0],[0,0],[0,0],[0,0]],"v":[[662,288],[486,298],[436,332],[412,402],[440,514],[518,568],[644,580],[662,460]],"c":true}],"e":[{"i":[[0,0],[0,0],[0,0],[0,0],[0,0],[0,0],[0,0],[0,0]],"o":[[0,0],[0,0],[0,0],[0,0],[0,0],[0,0],[0,0],[0,0]],"v":[[662,288],[486,298],[436,332],[412,402],[440,514],[518,568],[644,580],[662,460]],"c":true}]},{"i":{"x":0.833,"y":0.833},"o":{"x":0.167,"y":0.167},"n":"0p833_0p833_0p167_0p167","t":6.123,"s":[{"i":[[0,0],[0,0],[0,0],[0,0],[0,0],[0,0],[0,0],[0,0]],"o":[[0,0],[0,0],[0,0],[0,0],[0,0],[0,0],[0,0],[0,0]],"v":[[662,288],[486,298],[436,332],[412,402],[440,514],[518,568],[644,580],[662,460]],"c":true}],"e":[{"i":[[0,0],[0,0],[0,0],[0,0],[0,0],[0,0],[0,0],[0,0]],"o":[[0,0],[0,0],[0,0],[0,0],[0,0],[0,0],[0,0],[0,0]],"v":[[582,288],[406,298],[356,332],[332,402],[360,514],[438,568],[564,580],[582,460]],"c":true}]},{"i":{"x":0.833,"y":0.833},"o":{"x":0.167,"y":0.167},"n":"0p833_0p833_0p167_0p167","t":9.184,"s":[{"i":[[0,0],[0,0],[0,0],[0,0],[0,0],[0,0],[0,0],[0,0]],"o":[[0,0],[0,0],[0,0],[0,0],[0,0],[0,0],[0,0],[0,0]],"v":[[582,288],[406,298],[356,332],[332,402],[360,514],[438,568],[564,580],[582,460]],"c":true}],"e":[{"i":[[0,0],[0,0],[0,0],[0,0],[0,0],[0,0],[0,0],[0,0]],"o":[[0,0],[0,0],[0,0],[0,0],[0,0],[0,0],[0,0],[0,0]],"v":[[542,208],[374,214.896],[260,318.896],[158,426],[320,634],[398,688],[564,580],[582,460]],"c":true}]},{"i":{"x":0.833,"y":0.833},"o":{"x":0.167,"y":0.167},"n":"0p833_0p833_0p167_0p167","t":13,"s":[{"i":[[0,0],[0,0],[0,0],[0,0],[0,0],[0,0],[0,0],[0,0]],"o":[[0,0],[0,0],[0,0],[0,0],[0,0],[0,0],[0,0],[0,0]],"v":[[542,208],[374,214.896],[260,318.896],[158,426],[320,634],[398,688],[564,580],[582,460]],"c":true}],"e":[{"i":[[0,0],[0,0],[0,0],[0,0],[0,0],[0,0],[0,0],[0,0]],"o":[[0,0],[0,0],[0,0],[0,0],[0,0],[0,0],[0,0],[0,0]],"v":[[542,208],[406,218],[316,282],[202,402],[262,686],[517.5,756],[564,580],[582,460]],"c":true}]},{"i":{"x":0.833,"y":0.833},"o":{"x":0.167,"y":0.167},"n":"0p833_0p833_0p167_0p167","t":15,"s":[{"i":[[0,0],[0,0],[0,0],[0,0],[0,0],[0,0],[0,0],[0,0]],"o":[[0,0],[0,0],[0,0],[0,0],[0,0],[0,0],[0,0],[0,0]],"v":[[542,208],[406,218],[316,282],[202,402],[262,686],[517.5,756],[564,580],[582,460]],"c":true}],"e":[{"i":[[0,0],[0,0],[0,0],[0,0],[0,0],[0,0],[0,0],[0,0]],"o":[[0,0],[0,0],[0,0],[0,0],[0,0],[0,0],[0,0],[0,0]],"v":[[542,208],[406,218],[316,262.392],[176.68,452],[273.765,678.157],[517.827,737.699],[564,580],[582,460]],"c":true}]},{"i":{"x":0.833,"y":0.833},"o":{"x":0.167,"y":0.167},"n":"0p833_0p833_0p167_0p167","t":16,"s":[{"i":[[0,0],[0,0],[0,0],[0,0],[0,0],[0,0],[0,0],[0,0]],"o":[[0,0],[0,0],[0,0],[0,0],[0,0],[0,0],[0,0],[0,0]],"v":[[542,208],[406,218],[316,262.392],[176.68,452],[273.765,678.157],[517.827,737.699],[564,580],[582,460]],"c":true}],"e":[{"i":[[0,0],[0,0],[0,0],[0,0],[0,0],[0,0],[0,0],[0,0]],"o":[[0,0],[0,0],[0,0],[0,0],[0,0],[0,0],[0,0],[0,0]],"v":[[542,208],[406,218],[316,252],[252,402],[280,674],[518,728],[564,580],[582,460]],"c":true}]},{"i":{"x":0.833,"y":0.833},"o":{"x":0.167,"y":0.167},"n":"0p833_0p833_0p167_0p167","t":16.53,"s":[{"i":[[0,0],[0,0],[0,0],[0,0],[0,0],[0,0],[0,0],[0,0]],"o":[[0,0],[0,0],[0,0],[0,0],[0,0],[0,0],[0,0],[0,0]],"v":[[542,208],[406,218],[316,252],[252,402],[280,674],[518,728],[564,580],[582,460]],"c":true}],"e":[{"i":[[0,0],[0,0],[0,0],[0,0],[0,0],[0,0],[0,0],[0,0]],"o":[[0,0],[0,0],[0,0],[0,0],[0,0],[0,0],[0,0],[0,0]],"v":[[542,208],[406,218],[316,252],[163.995,356],[191.997,846.005],[518,744.005],[564,580],[549.989,468.003]],"c":true}]},{"i":{"x":0.833,"y":0.833},"o":{"x":0.167,"y":0.167},"n":"0p833_0p833_0p167_0p167","t":18,"s":[{"i":[[0,0],[0,0],[0,0],[0,0],[0,0],[0,0],[0,0],[0,0]],"o":[[0,0],[0,0],[0,0],[0,0],[0,0],[0,0],[0,0],[0,0]],"v":[[542,208],[406,218],[316,252],[163.995,356],[191.997,846.005],[518,744.005],[564,580],[549.989,468.003]],"c":true}],"e":[{"i":[[0,0],[0,0],[0,0],[0,0],[0,0],[0,0],[0,0],[0,0]],"o":[[0,0],[0,0],[0,0],[0,0],[0,0],[0,0],[0,0],[0,0]],"v":[[542,208],[406,218],[316,252],[172,402],[240,754],[518,808],[564,580],[422,500]],"c":true}]},{"i":{"x":0.833,"y":0.833},"o":{"x":0.167,"y":0.167},"n":"0p833_0p833_0p167_0p167","t":23.878,"s":[{"i":[[0,0],[0,0],[0,0],[0,0],[0,0],[0,0],[0,0],[0,0]],"o":[[0,0],[0,0],[0,0],[0,0],[0,0],[0,0],[0,0],[0,0]],"v":[[542,208],[406,218],[316,252],[172,402],[240,754],[518,808],[564,580],[422,500]],"c":true}],"e":[{"i":[[0,0],[0,0],[0,0],[0,0],[0,0],[0,0],[0,0],[0,0]],"o":[[0,0],[0,0],[0,0],[0,0],[0,0],[0,0],[0,0],[0,0]],"v":[[496.657,208],[406,218],[316,252],[172,402],[240,754],[518,808],[564,580],[328.657,514]],"c":true}]},{"i":{"x":0.833,"y":0.833},"o":{"x":0.167,"y":0.167},"n":"0p833_0p833_0p167_0p167","t":26,"s":[{"i":[[0,0],[0,0],[0,0],[0,0],[0,0],[0,0],[0,0],[0,0]],"o":[[0,0],[0,0],[0,0],[0,0],[0,0],[0,0],[0,0],[0,0]],"v":[[496.657,208],[406,218],[316,252],[172,402],[240,754],[518,808],[564,580],[328.657,514]],"c":true}],"e":[{"i":[[0,0],[0,0],[0,0],[0,0],[0,0],[0,0],[0,0],[0,0]],"o":[[0,0],[0,0],[0,0],[0,0],[0,0],[0,0],[0,0],[0,0]],"v":[[422,208],[406,218],[316,252],[172,402],[240,754],[518,808],[564,580],[302,540]],"c":true}]},{"t":30.0000012219251}]},"o":{"k":100},"x":{"k":0},"nm":"Mask 1"}],"w":1024,"h":1024,"ip":0,"op":63.0000025660426,"st":0,"bm":0,"sr":1}]},{"id":"comp_7","layers":[{"ddd":0,"ind":0,"ty":4,"nm":"pie_fill","td":1,"ks":{"o":{"k":100},"r":{"k":0},"p":{"k":[512,512,0]},"a":{"k":[0,0,0]},"s":{"k":[100,100,100]}},"ao":0,"shapes":[{"d":1,"ty":"el","s":{"k":[285,285]},"p":{"k":[0,0]},"nm":"Ellipse Path 1","mn":"ADBE Vector Shape - Ellipse"},{"ty":"tm","s":{"k":55.7,"ix":1},"e":{"k":100,"ix":2},"o":{"k":0,"ix":3},"m":1,"ix":2,"nm":"Trim Paths 1","mn":"ADBE Vector Filter - Trim"},{"ty":"st","c":{"k":[0,0.5,0.55,1]},"o":{"k":100},"w":{"k":285},"lc":1,"lj":1,"ml":1,"nm":"Stroke 1","mn":"ADBE Vector Graphic - Stroke"}],"ip":0,"op":392.000015966487,"st":32.0000013033867,"bm":0,"sr":1},{"ddd":0,"ind":1,"ty":4,"nm":"Shape Layer 1","tt":1,"ks":{"o":{"k":100},"r":{"k":[{"i":{"x":[0.667],"y":[1]},"o":{"x":[0.333],"y":[0]},"n":["0p667_1_0p333_0"],"t":0,"s":[351],"e":[-158]},{"t":31.0000012626559}]},"p":{"k":[517.5,510,0]},"a":{"k":[5.5,-2,0]},"s":{"k":[100,100,100]}},"ao":0,"shapes":[{"ty":"gr","it":[{"ind":0,"ty":"sh","ks":{"k":{"i":[[-72.425,0],[-0.004,0],[0,0],[49.318,49.102],[0,69.44],[-49.319,49.103],[-69.746,0],[0,0],[51.216,-50.991],[-0.001,-72.112],[-51.215,-50.99]],"o":[[0.005,0],[0,0],[-69.747,0.001],[-49.318,-49.102],[-0.001,-69.441],[49.319,-49.102],[0,0],[-72.429,0],[-51.216,50.992],[0,72.111],[51.212,50.987]],"v":[[4.675,267.969],[4.679,267.969],[4.679,257.969],[-179.957,181.828],[-256.436,-1.997],[-179.956,-185.825],[4.681,-261.969],[4.681,-271.969],[-187.059,-192.897],[-266.479,-1.997],[-187.06,188.899]],"c":true}},"nm":"Path 1","mn":"ADBE Vector Shape - Group"},{"ind":1,"ty":"sh","ks":{"k":{"i":[[38.829,22.319],[17.423,64.733],[-33.657,58.041],[-65.021,17.345],[0,0],[32.316,-55.727],[-16.728,-62.158],[-55.972,-32.174],[-62.43,16.655],[0,0],[21.891,0.001]],"o":[[-58.296,-33.509],[-17.422,-64.738],[33.657,-58.041],[0,0],[-62.431,16.654],[-32.315,55.728],[16.729,62.152],[55.973,32.173],[0,0],[-21.712,5.792],[-43.666,0]],"v":[[-121.309,215.416],[-238.728,63.07],[-213.551,-127.327],[-60.526,-244.229],[-57.927,-234.57],[-204.853,-122.327],[-229.026,60.482],[-116.287,206.756],[67.322,230.823],[69.922,240.483],[4.288,249.139]],"c":true}},"nm":"Path 2","mn":"ADBE Vector Shape - Group"},{"ind":2,"ty":"sh","ks":{"k":{"i":[[20.059,5.351],[31.099,53.629],[-16.099,59.816],[-53.866,30.964],[0,0],[15.404,-57.235],[-29.759,-51.317],[-57.487,-15.337],[-51.543,29.628],[0,0],[40.352,0.002]],"o":[[-60.079,-16.027],[-31.101,-53.631],[16.099,-59.815],[0,0],[-51.543,29.629],[-15.404,57.236],[29.759,51.315],[57.487,15.336],[0,0],[-35.883,20.626],[-20.224,0]],"v":[[-55.524,222.183],[-196.918,114.165],[-220.182,-61.761],[-111.685,-202.535],[-106.663,-193.875],[-210.479,-59.172],[-188.22,109.165],[-52.925,212.524],[116.152,190.362],[121.175,199.022],[5.123,230.182]],"c":true}},"nm":"Path 3","mn":"ADBE Vector Shape - Group"},{"ind":3,"ty":"sh","ks":{"k":{"i":[[40.363,40.185],[0,56.835],[-40.365,40.186],[0,0],[0,-54.164],[-38.467,-38.301],[-79.41,79.059],[0,0],[57.083,0],[0.004,0]],"o":[[-40.364,-40.189],[0,-56.836],[0,0],[-38.468,38.297],[0,54.164],[79.412,79.059],[0,0],[-40.365,40.188],[-0.004,0],[-57.08,0]],"v":[[-146.295,148.799],[-208.89,-1.657],[-146.294,-152.111],[-139.192,-145.04],[-198.846,-1.657],[-139.193,141.729],[148.838,141.727],[155.939,148.797],[4.823,211.118],[4.821,211.118]],"c":true}},"nm":"Path 4","mn":"ADBE Vector Shape - Group"},{"ind":4,"ty":"sh","ks":{"k":{"i":[[29.978,17.232],[-53.641,92.502],[0,0],[-88.112,-50.649],[-47.607,12.7],[-24.644,42.497],[0,0],[50.2,-13.392],[16.9,0]],"o":[[-92.909,-53.406],[0,0],[-50.871,87.726],[42.686,24.537],[47.607,-12.701],[0,0],[-25.984,44.81],[-16.762,4.472],[-33.713,-0.001]],"v":[[-92.357,166.176],[-163.573,-98.436],[-154.875,-93.436],[-87.336,157.516],[52.682,175.871],[164.723,90.274],[173.421,95.274],[55.28,185.53],[4.608,192.213]],"c":true}},"nm":"Path 5","mn":"ADBE Vector Shape - Group"},{"ind":5,"ty":"sh","ks":{"k":{"i":[[15.112,4.031],[-25.032,93.019],[0,0],[-88.078,-23.498],[-14.368,0],[-25.479,14.646],[-11.433,42.481],[0,0],[40.577,-23.325],[30.394,0]],"o":[[-93.427,-24.925],[0,0],[-23.6,87.693],[14.25,3.802],[28.651,-0.002],[38.254,-21.99],[0,0],[-12.127,45.06],[-27.029,15.536],[-15.238,0]],"v":[[-40.359,167.163],[-164.397,-46.734],[-154.694,-44.147],[-37.76,157.503],[5.312,163.185],[87.728,141.056],[164.778,41.081],[174.48,43.668],[92.75,149.716],[5.329,173.189]],"c":true}},"nm":"Path 6","mn":"ADBE Vector Shape - Group"},{"ind":6,"ty":"sh","ks":{"k":{"i":[[0,85.787],[0,0],[-80.629,-0.001],[0,80.273],[0,0],[86.165,0]],"o":[[0,0],[0,80.272],[80.627,0],[0,0],[0,85.788],[-86.167,-0.001]],"v":[[-151.101,-1.516],[-141.057,-1.516],[5.169,144.065],[151.391,-1.516],[161.435,-1.516],[5.169,154.065]],"c":true}},"nm":"Path 7","mn":"ADBE Vector Shape - Group"},{"ind":7,"ty":"sh","ks":{"k":{"i":[[16.396,60.918],[0,0],[-67.688,18.06],[18.137,67.383],[0,0],[73.03,-19.484],[11.717,0]],"o":[[0,0],[18.134,67.382],[67.681,-18.056],[0,0],[19.568,72.709],[-11.843,3.159],[-60.534,0]],"v":[[-127.152,33.801],[-117.449,31.213],[38.185,120.672],[128.036,-34.277],[137.739,-36.865],[40.783,130.333],[5.327,134.999]],"c":true}},"nm":"Path 8","mn":"ADBE Vector Shape - Group"},{"ind":8,"ty":"sh","ks":{"k":{"i":[[10.163,2.711],[15.756,27.169],[0,0],[-27.847,-7.429],[-24.967,14.351],[-7.462,27.724],[14.414,24.856],[0,0],[8.155,-30.304],[27.289,-15.685],[20.443,0]],"o":[[-30.438,-8.12],[0,0],[14.414,24.856],[27.843,7.429],[24.966,-14.35],[7.46,-27.724],[0,0],[15.756,27.17],[-8.155,30.304],[-18.178,10.449],[-10.245,0]],"v":[[-25.122,111.867],[-96.754,57.143],[-88.056,52.143],[-22.521,102.208],[59.374,91.473],[109.659,26.228],[98.876,-55.309],[107.574,-60.309],[119.36,28.817],[64.396,100.133],[5.603,115.919]],"c":true}},"nm":"Path 9","mn":"ADBE Vector Shape - Group"},{"ind":9,"ty":"sh","ks":{"k":{"i":[[18.662,18.582],[0,0],[-23.714,0],[-16.77,16.695],[34.611,34.461],[0,0],[38.529,-38.361],[26.396,-0.001],[0.002,0]],"o":[[0,0],[16.768,16.694],[23.712,0],[34.611,-34.462],[0,0],[38.529,38.361],[-18.665,18.583],[-0.002,0],[-26.395,0]],"v":[[-64.364,67.912],[-57.263,60.84],[5.513,86.729],[68.288,60.84],[68.288,-64.158],[75.39,-71.229],[75.39,67.911],[5.513,96.729],[5.512,96.729]],"c":true}},"nm":"Path 10","mn":"ADBE Vector Shape - Group"},{"ind":10,"ty":"sh","ks":{"k":{"i":[[12.592,7.239],[0,0],[-11.891,0],[-12.975,22.374],[33.489,19.251],[0,0],[22.104,-38.117],[27.731,0.001]],"o":[[0,0],[11.018,6.333],[24.256,-0.002],[19.334,-33.342],[0,0],[38.286,22.008],[-14.835,25.58],[-13.592,-0.001]],"v":[[-34.499,67.369],[-29.478,58.709],[5.47,68.05],[66.324,33.152],[40.653,-62.228],[45.675,-70.888],[75.022,38.152],[5.453,78.048]],"c":true}},"nm":"Path 11","mn":"ADBE Vector Shape - Group"},{"ind":11,"ty":"sh","ks":{"k":{"i":[[5.225,1.394],[0,0],[-7.204,26.768],[6.741,11.626],[13.023,3.475],[0,0],[-8.084,-13.939],[4.184,-15.546],[26.722,0]],"o":[[0,0],[26.885,7.172],[3.49,-12.967],[-6.743,-11.626],[0,0],[15.615,4.165],[8.083,13.939],[-7.239,26.892],[-5.169,0]],"v":[[-10.027,56.328],[-7.429,46.669],[54.396,11.131],[49.354,-27.006],[18.702,-50.422],[21.302,-60.082],[58.053,-32.006],[64.1,13.719],[5.622,58.388]],"c":true}},"nm":"Path 12","mn":"ADBE Vector Shape - Group"},{"ind":12,"ty":"sh","ks":{"k":{"i":[[0,0],[0,17.2],[17.276,0],[0,0],[0,-22.714],[22.814,0]],"o":[[17.276,0],[0,-17.2],[0,0],[22.814,0],[0,22.714],[0,0]],"v":[[5.652,29.191],[36.983,-2.002],[5.652,-33.195],[5.652,-43.195],[47.027,-2.002],[5.652,39.191]],"c":true}},"nm":"Path 13","mn":"ADBE Vector Shape - Group"},{"ty":"st","c":{"k":[1,1,1,1]},"o":{"k":100},"w":{"k":0},"lc":1,"lj":1,"ml":4,"nm":"Stroke 1","mn":"ADBE Vector Graphic - Stroke"},{"ty":"fl","c":{"k":[0,1,0.97,1]},"o":{"k":100},"nm":"Fill 1","mn":"ADBE Vector Graphic - Fill"},{"ty":"tr","p":{"k":[0,0],"ix":2},"a":{"k":[0,0],"ix":1},"s":{"k":[100,100],"ix":3},"r":{"k":0,"ix":6},"o":{"k":100,"ix":7},"sk":{"k":0,"ix":4},"sa":{"k":0,"ix":5},"nm":"Transform"}],"nm":"Shape 1","np":15,"mn":"ADBE Vector Group"}],"ip":0,"op":360.000014663101,"st":0,"bm":0,"sr":1}]},{"id":"comp_8","layers":[{"ddd":0,"ind":0,"ty":0,"nm":"end_spark","refId":"comp_9","ks":{"o":{"k":100},"r":{"k":45},"p":{"k":[512,512,0]},"a":{"k":[512,512,0]},"s":{"k":[145,145,100]}},"ao":0,"w":1024,"h":1024,"ip":50.0000020365418,"op":56.0000022809268,"st":50.0000020365418,"bm":0,"sr":1},{"ddd":0,"ind":1,"ty":4,"nm":"pie_stroke_center_ball","ks":{"o":{"k":100},"r":{"k":0},"p":{"k":[512,512,0]},"a":{"k":[0,0,0]},"s":{"k":[{"i":{"x":[0.545,0.545,0.567],"y":[0.84,0.84,0.567]},"o":{"x":[0.213,0.213,0.213],"y":[0,0,0.213]},"n":["0p545_0p84_0p213_0","0p545_0p84_0p213_0","0p567_0p567_0p213_0p213"],"t":24,"s":[100,100,100],"e":[191,191,100]},{"i":{"x":[0.567,0.567,0.567],"y":[1,1,0.567]},"o":{"x":[0.363,0.363,0.318],"y":[0.609,0.609,0.318]},"n":["0p567_1_0p363_0p609","0p567_1_0p363_0p609","0p567_0p567_0p318_0p318"],"t":30,"s":[191,191,100],"e":[211,211,100]},{"i":{"x":[0.94,0.94,0.667],"y":[0.334,0.334,0.667]},"o":{"x":[0.887,0.887,0.318],"y":[0,0,0.318]},"n":["0p94_0p334_0p887_0","0p94_0p334_0p887_0","0p667_0p667_0p318_0p318"],"t":36,"s":[211,211,100],"e":[0,0,100]},{"t":50.0000020365418}]}},"ao":0,"shapes":[{"d":1,"ty":"el","s":{"k":[20,20]},"p":{"k":[0,0]},"nm":"Ellipse Path 1","mn":"ADBE Vector Shape - Ellipse"},{"ty":"tm","s":{"k":0,"ix":1},"e":{"k":100,"ix":2},"o":{"k":0,"ix":3},"m":1,"ix":2,"nm":"Trim Paths 1","mn":"ADBE Vector Filter - Trim"},{"ty":"fl","c":{"k":[0.17,0.99,0.96,1]},"o":{"k":100},"nm":"Fill 1","mn":"ADBE Vector Graphic - Fill"},{"ty":"st","c":{"k":[0,1,0.97,1]},"o":{"k":100},"w":{"k":10},"lc":1,"lj":1,"ml":1,"nm":"Stroke 1","mn":"ADBE Vector Graphic - Stroke"}],"ip":0,"op":52.0000021180034,"st":-109.000004439661,"bm":0,"sr":1},{"ddd":0,"ind":2,"ty":4,"nm":"pie_stroke_rear","ks":{"o":{"k":100},"r":{"k":0},"p":{"k":[512,512,0]},"a":{"k":[0,0,0]},"s":{"k":[100,100,100]}},"ao":0,"shapes":[{"ty":"gr","it":[{"ind":0,"ty":"sh","ks":{"k":[{"i":{"x":0.833,"y":1},"o":{"x":0.167,"y":0},"n":"0p833_1_0p167_0","t":6,"s":[{"i":[[0,0],[0,0]],"o":[[0,0],[0,0]],"v":[[-2,2],[-1.967,-294.75]],"c":false}],"e":[{"i":[[0,0],[0,0]],"o":[[0,0],[0,0]],"v":[[-2,2],[-1.967,-294.75]],"c":false}]},{"i":{"x":0.833,"y":1},"o":{"x":0.167,"y":0},"n":"0p833_1_0p167_0","t":24,"s":[{"i":[[0,0],[0,0]],"o":[[0,0],[0,0]],"v":[[-2,2],[-1.967,-294.75]],"c":false}],"e":[{"i":[[0,0],[0,0]],"o":[[0,0],[0,0]],"v":[[-2,2],[-2.269,-4.192]],"c":false}]},{"t":29.0000011811942}]},"nm":"Path 1","mn":"ADBE Vector Shape - Group"},{"ty":"st","c":{"k":[0,1,0.97,1]},"o":{"k":100},"w":{"k":20},"lc":1,"lj":1,"ml":4,"nm":"Stroke 1","mn":"ADBE Vector Graphic - Stroke"},{"ty":"tr","p":{"k":[0,0],"ix":2},"a":{"k":[0,0],"ix":1},"s":{"k":[100,100],"ix":3},"r":{"k":[{"i":{"x":[0.833],"y":[1]},"o":{"x":[0.167],"y":[0]},"n":["0p833_1_0p167_0"],"t":6,"s":[360],"e":[166]},{"t":29.0000011811942}],"ix":6},"o":{"k":100,"ix":7},"sk":{"k":0,"ix":4},"sa":{"k":0,"ix":5},"nm":"Transform"}],"nm":"Shape 1","np":2,"mn":"ADBE Vector Group"}],"ip":0,"op":30.0000012219251,"st":-103.000004195276,"bm":0,"sr":1},{"ddd":0,"ind":3,"ty":4,"nm":"pie_stroke_front","ks":{"o":{"k":100},"r":{"k":0},"p":{"k":[512,512,0]},"a":{"k":[0,0,0]},"s":{"k":[100,100,100]}},"ao":0,"shapes":[{"ty":"gr","it":[{"ind":0,"ty":"sh","ks":{"k":{"i":[[0,0],[0,0]],"o":[[0,0],[0,0]],"v":[[-2,2],[-2,-292]],"c":false}},"nm":"Path 1","mn":"ADBE Vector Shape - Group"},{"ty":"st","c":{"k":[0,1,0.97,1]},"o":{"k":100},"w":{"k":20},"lc":1,"lj":1,"ml":4,"nm":"Stroke 1","mn":"ADBE Vector Graphic - Stroke"},{"ty":"tr","p":{"k":[0,0],"ix":2},"a":{"k":[0,0],"ix":1},"s":{"k":[100,100],"ix":3},"r":{"k":[{"i":{"x":[0.712],"y":[0.712]},"o":{"x":[0.158],"y":[0.158]},"n":["0p712_0p712_0p158_0p158"],"t":6,"s":[-157],"e":[-157]},{"i":{"x":[0.768],"y":[1]},"o":{"x":[0.422],"y":[0]},"n":["0p768_1_0p422_0"],"t":18,"s":[-157],"e":[-164]},{"t":25.0000010182709}],"ix":6},"o":{"k":100,"ix":7},"sk":{"k":0,"ix":4},"sa":{"k":0,"ix":5},"nm":"Transform"}],"nm":"Shape 1","np":2,"mn":"ADBE Vector Group"}],"ip":0,"op":25.0000010182709,"st":-103.000004195276,"bm":0,"sr":1},{"ddd":0,"ind":4,"ty":4,"nm":"pie_stroke_arc","ks":{"o":{"k":100},"r":{"k":0},"p":{"k":[512,512,0]},"a":{"k":[0,0,0]},"s":{"k":[100,100,100]}},"ao":0,"shapes":[{"d":1,"ty":"el","s":{"k":[570,570]},"p":{"k":[0,0]},"nm":"Ellipse Path 1","mn":"ADBE Vector Shape - Ellipse"},{"ty":"tm","s":{"k":[{"i":{"x":[0.833],"y":[0.833]},"o":{"x":[0.167],"y":[0.167]},"n":["0p833_0p833_0p167_0p167"],"t":19,"s":[55.7],"e":[55.2]},{"i":{"x":[0.833],"y":[0.833]},"o":{"x":[0.167],"y":[0.167]},"n":["0p833_0p833_0p167_0p167"],"t":21,"s":[55.2],"e":[54.3]},{"t":23.0000009368092}],"ix":1},"e":{"k":[{"i":{"x":[0.833],"y":[0.833]},"o":{"x":[0.167],"y":[0.167]},"n":["0p833_0p833_0p167_0p167"],"t":6,"s":[100],"e":[98.95]},{"i":{"x":[0.833],"y":[0.833]},"o":{"x":[0.167],"y":[0.167]},"n":["0p833_0p833_0p167_0p167"],"t":7,"s":[98.95],"e":[95.133]},{"i":{"x":[0.833],"y":[0.833]},"o":{"x":[0.167],"y":[0.167]},"n":["0p833_0p833_0p167_0p167"],"t":9,"s":[95.133],"e":[90.517]},{"i":{"x":[0.833],"y":[0.833]},"o":{"x":[0.167],"y":[0.167]},"n":["0p833_0p833_0p167_0p167"],"t":11,"s":[90.517],"e":[77.5]},{"i":{"x":[0.833],"y":[0.833]},"o":{"x":[0.167],"y":[0.167]},"n":["0p833_0p833_0p167_0p167"],"t":16,"s":[77.5],"e":[55.7]},{"t":24.00000097754}],"ix":2},"o":{"k":0,"ix":3},"m":1,"ix":2,"nm":"Trim Paths 1","mn":"ADBE Vector Filter - Trim"},{"ty":"st","c":{"k":[0,1,0.97,1]},"o":{"k":100},"w":{"k":20},"lc":1,"lj":1,"ml":1,"nm":"Stroke 1","mn":"ADBE Vector Graphic - Stroke"}],"ip":0,"op":25.0000010182709,"st":-103.000004195276,"bm":0,"sr":1},{"ddd":0,"ind":5,"ty":4,"nm":"pie_fill","ks":{"o":{"k":100},"r":{"k":0},"p":{"k":[512,512,0]},"a":{"k":[0,0,0]},"s":{"k":[100,100,100]}},"ao":0,"shapes":[{"d":1,"ty":"el","s":{"k":[285,285]},"p":{"k":[0,0]},"nm":"Ellipse Path 1","mn":"ADBE Vector Shape - Ellipse"},{"ty":"tm","s":{"k":[{"i":{"x":[0.833],"y":[0.833]},"o":{"x":[0.167],"y":[0.167]},"n":["0p833_0p833_0p167_0p167"],"t":22,"s":[55.7],"e":[54.6]},{"t":23.0000009368092}],"ix":1},"e":{"k":[{"i":{"x":[0.833],"y":[0.833]},"o":{"x":[0.167],"y":[0.167]},"n":["0p833_0p833_0p167_0p167"],"t":6,"s":[100],"e":[98.95]},{"i":{"x":[0.833],"y":[0.833]},"o":{"x":[0.167],"y":[0.167]},"n":["0p833_0p833_0p167_0p167"],"t":7,"s":[98.95],"e":[90.517]},{"i":{"x":[0.833],"y":[0.833]},"o":{"x":[0.167],"y":[0.167]},"n":["0p833_0p833_0p167_0p167"],"t":11,"s":[90.517],"e":[77.5]},{"i":{"x":[0.833],"y":[0.833]},"o":{"x":[0.167],"y":[0.167]},"n":["0p833_0p833_0p167_0p167"],"t":16,"s":[77.5],"e":[58.425]},{"i":{"x":[0.833],"y":[0.833]},"o":{"x":[0.167],"y":[0.167]},"n":["0p833_0p833_0p167_0p167"],"t":23,"s":[58.425],"e":[55.7]},{"t":24.00000097754}],"ix":2},"o":{"k":0,"ix":3},"m":1,"ix":2,"nm":"Trim Paths 1","mn":"ADBE Vector Filter - Trim"},{"ty":"st","c":{"k":[0,0.5,0.55,1]},"o":{"k":100},"w":{"k":285},"lc":1,"lj":1,"ml":1,"nm":"Stroke 1","mn":"ADBE Vector Graphic - Stroke"}],"ip":0,"op":24.00000097754,"st":-103.000004195276,"bm":0,"sr":1},{"ddd":0,"ind":6,"ty":4,"nm":"orange_dot","ks":{"o":{"k":100},"r":{"k":[{"i":{"x":[0.833],"y":[0.833]},"o":{"x":[0.167],"y":[0.167]},"n":["0p833_0p833_0p167_0p167"],"t":6,"s":[-360],"e":[-360]},{"i":{"x":[0.833],"y":[1]},"o":{"x":[0.167],"y":[0]},"n":["0p833_1_0p167_0"],"t":18,"s":[-360],"e":[-366]},{"t":24.00000097754}]},"p":{"k":[512,512,0]},"a":{"k":[50.5,50.5,0]},"s":{"k":[795,795,100]}},"ao":0,"shapes":[{"ty":"gr","it":[{"ind":0,"ty":"sh","ks":{"k":{"i":[[0,1.712],[1.712,0],[0,-1.712],[-1.713,0]],"o":[[0,-1.712],[-1.713,0],[0,1.712],[1.712,0]],"v":[[3.1,-0.001],[0.001,-3.101],[-3.1,-0.001],[0.001,3.101]],"c":true}},"nm":"Path 1","mn":"ADBE Vector Shape - Group"},{"ty":"fl","c":{"k":[0.96,0.41,0.18,1]},"o":{"k":100},"nm":"Fill 1","mn":"ADBE Vector Graphic - Fill"},{"ty":"tr","p":{"k":[31.198,96.003],"ix":2},"a":{"k":[0,0],"ix":1},"s":{"k":[{"i":{"x":[0.668,0.668],"y":[0.57,0.57]},"o":{"x":[0.333,0.333],"y":[0,0]},"n":["0p668_0p57_0p333_0","0p668_0p57_0p333_0"],"t":6,"s":[100,100],"e":[140,140]},{"i":{"x":[0.791,0.791],"y":[0.267,0.267]},"o":{"x":[0.596,0.596],"y":[-0.134,-0.134]},"n":["0p791_0p267_0p596_-0p134","0p791_0p267_0p596_-0p134"],"t":18,"s":[140,140],"e":[20,20]},{"t":24.00000097754}],"ix":3},"r":{"k":0,"ix":6},"o":{"k":100,"ix":7},"sk":{"k":0,"ix":4},"sa":{"k":0,"ix":5},"nm":"Transform"}],"nm":"orange_dot","np":2,"mn":"ADBE Vector Group"}],"ip":0,"op":25.0000010182709,"st":-111.000004521123,"bm":0,"sr":1},{"ddd":0,"ind":7,"ty":4,"nm":"orange_stroke 3","ks":{"o":{"k":100},"r":{"k":0},"p":{"k":[566,563,0]},"a":{"k":[50.5,50.5,0]},"s":{"k":[100,100,100]}},"ao":0,"shapes":[{"ty":"gr","it":[{"d":1,"ty":"el","s":{"k":[789,789]},"p":{"k":[0,0]},"nm":"Ellipse Path 1","mn":"ADBE Vector Shape - Ellipse"},{"ty":"tm","s":{"k":55.9,"ix":1},"e":{"k":[{"i":{"x":[0.981],"y":[0.315]},"o":{"x":[0.175],"y":[0]},"n":["0p981_0p315_0p175_0"],"t":4,"s":[100],"e":[56]},{"t":20.0000008146167}],"ix":2},"o":{"k":0,"ix":3},"m":1,"ix":2,"nm":"Trim Paths 1","mn":"ADBE Vector Filter - Trim"},{"ty":"st","c":{"k":[0.96,0.41,0.22,1]},"o":{"k":100},"w":{"k":18},"lc":1,"lj":1,"ml":1,"nm":"Stroke 1","mn":"ADBE Vector Graphic - Stroke"},{"ty":"tr","p":{"k":[0,0],"ix":2},"a":{"k":[0,0],"ix":1},"s":{"k":[100,100],"ix":3},"r":{"k":0,"ix":6},"o":{"k":100,"ix":7},"sk":{"k":0,"ix":4},"sa":{"k":0,"ix":5},"nm":"Transform"}],"nm":"orange_stroke","np":3,"mn":"ADBE Vector Group"}],"ip":0,"op":21.0000008553475,"st":0,"bm":0,"sr":1},{"ddd":0,"ind":8,"ty":4,"nm":"bg","ks":{"o":{"k":100},"r":{"k":0},"p":{"k":[510,511,0]},"a":{"k":[-5.591,-1.585,0]},"s":{"k":[{"i":{"x":[0.948,0.948,0.667],"y":[0.773,0.773,0.667]},"o":{"x":[0.998,0.998,0.333],"y":[-0.163,-0.163,0.333]},"n":["0p948_0p773_0p998_-0p163","0p948_0p773_0p998_-0p163","0p667_0p667_0p333_0p333"],"t":38,"s":[100,100,100],"e":[0,0,100]},{"t":50.0000020365418}]}},"ao":0,"shapes":[{"ty":"gr","it":[{"d":1,"ty":"el","s":{"k":[789,789]},"p":{"k":[0,0]},"nm":"Ellipse Path 1","mn":"ADBE Vector Shape - Ellipse"},{"ty":"st","c":{"k":[0.82,0.84,0.87,1]},"o":{"k":100},"w":{"k":18},"lc":1,"lj":1,"ml":1,"nm":"Stroke 1","mn":"ADBE Vector Graphic - Stroke"},{"ty":"tr","p":{"k":[0,0],"ix":2},"a":{"k":[0,0],"ix":1},"s":{"k":[100,100],"ix":3},"r":{"k":0,"ix":6},"o":{"k":100,"ix":7},"sk":{"k":0,"ix":4},"sa":{"k":0,"ix":5},"nm":"Transform"}],"nm":"strokeee","np":2,"mn":"ADBE Vector Group"}],"ip":0,"op":51.0000020772726,"st":28.0000011404634,"bm":0,"sr":1},{"ddd":0,"ind":9,"ty":4,"nm":"clock_ticks","ks":{"o":{"k":100},"r":{"k":0},"p":{"k":[512,512,0]},"a":{"k":[50.5,50.5,0]},"s":{"k":[{"i":{"x":[0.948,0.948,0.667],"y":[0.948,0.948,0.667]},"o":{"x":[0.998,0.998,0.333],"y":[0.998,0.998,0.333]},"n":["0p948_0p948_0p998_0p998","0p948_0p948_0p998_0p998","0p667_0p667_0p333_0p333"],"t":38,"s":[795,795,100],"e":[795,795,100]},{"t":50.0000020365418}]}},"ao":0,"shapes":[{"ty":"gr","it":[{"ind":0,"ty":"sh","ks":{"k":[{"i":{"x":0.667,"y":1},"o":{"x":0.333,"y":0},"n":"0p667_1_0p333_0","t":34,"s":[{"i":[[0,0],[0,0],[0,0],[0,0]],"o":[[0,0],[0,0],[0,0],[0,0]],"v":[[1,2.794],[-1,2.794],[-1,-2.794],[1,-2.794]],"c":true}],"e":[{"i":[[0,0],[0,0],[0,0],[0,0]],"o":[[0,0],[0,0],[0,0],[0,0]],"v":[[1,-1.924],[-1,-1.924],[-1,-2.794],[1,-2.794]],"c":true}]},{"t":38.0000015477717}]},"nm":"Path 1","mn":"ADBE Vector Shape - Group"},{"ty":"tr","p":{"k":[50.444,3.793],"ix":2},"a":{"k":[0,0],"ix":1},"s":{"k":[100,100],"ix":3},"r":{"k":0,"ix":6},"o":{"k":100,"ix":7},"sk":{"k":0,"ix":4},"sa":{"k":0,"ix":5},"nm":"Transform"}],"nm":"12","np":1,"mn":"ADBE Vector Group"},{"ty":"gr","it":[{"ind":0,"ty":"sh","ks":{"k":[{"i":{"x":0.667,"y":1},"o":{"x":0.333,"y":0},"n":"0p667_1_0p333_0","t":36,"s":[{"i":[[0,0],[0,0],[0,0],[0,0]],"o":[[0,0],[0,0],[0,0],[0,0]],"v":[[2.794,1],[-2.794,1],[-2.794,-1],[2.794,-1]],"c":true}],"e":[{"i":[[0,0],[0,0],[0,0],[0,0]],"o":[[0,0],[0,0],[0,0],[0,0]],"v":[[-2.112,1],[-2.794,1],[-2.794,-1],[-2.112,-1]],"c":true}]},{"t":40.0000016292334}]},"nm":"Path 1","mn":"ADBE Vector Shape - Group"},{"ty":"tr","p":{"k":[3.793,50.445],"ix":2},"a":{"k":[0,0],"ix":1},"s":{"k":[100,100],"ix":3},"r":{"k":0,"ix":6},"o":{"k":100,"ix":7},"sk":{"k":0,"ix":4},"sa":{"k":0,"ix":5},"nm":"Transform"}],"nm":"9","np":1,"mn":"ADBE Vector Group"},{"ty":"gr","it":[{"ind":0,"ty":"sh","ks":{"k":[{"i":{"x":0.667,"y":1},"o":{"x":0.333,"y":0},"n":"0p667_1_0p333_0","t":38,"s":[{"i":[[0,0],[0,0],[0,0],[0,0]],"o":[[0,0],[0,0],[0,0],[0,0]],"v":[[1,2.794],[-1,2.794],[-1,-2.794],[1,-2.794]],"c":true}],"e":[{"i":[[0,0],[0,0],[0,0],[0,0]],"o":[[0,0],[0,0],[0,0],[0,0]],"v":[[1,2.794],[-1,2.794],[-1,2.237],[1,2.237]],"c":true}]},{"t":42.0000017106951}]},"nm":"Path 1","mn":"ADBE Vector Shape - Group"},{"ty":"tr","p":{"k":[50.444,97.094],"ix":2},"a":{"k":[0,0],"ix":1},"s":{"k":[100,100],"ix":3},"r":{"k":0,"ix":6},"o":{"k":100,"ix":7},"sk":{"k":0,"ix":4},"sa":{"k":0,"ix":5},"nm":"Transform"}],"nm":"6","np":1,"mn":"ADBE Vector Group"},{"ty":"gr","it":[{"ind":0,"ty":"sh","ks":{"k":[{"i":{"x":0.667,"y":1},"o":{"x":0.333,"y":0},"n":"0p667_1_0p333_0","t":40,"s":[{"i":[[0,0],[0,0],[0,0],[0,0]],"o":[[0,0],[0,0],[0,0],[0,0]],"v":[[2.794,1],[-2.794,1],[-2.794,-1],[2.794,-1]],"c":true}],"e":[{"i":[[0,0],[0,0],[0,0],[0,0]],"o":[[0,0],[0,0],[0,0],[0,0]],"v":[[2.794,1],[2.112,1],[2.112,-1],[2.794,-1]],"c":true}]},{"t":44.0000017921567}]},"nm":"Path 1","mn":"ADBE Vector Shape - Group"},{"ty":"tr","p":{"k":[97.094,50.445],"ix":2},"a":{"k":[0,0],"ix":1},"s":{"k":[100,100],"ix":3},"r":{"k":0,"ix":6},"o":{"k":100,"ix":7},"sk":{"k":0,"ix":4},"sa":{"k":0,"ix":5},"nm":"Transform"}],"nm":"3","np":1,"mn":"ADBE Vector Group"},{"ty":"mm","mm":2,"nm":"Merge Paths 1","mn":"ADBE Vector Filter - Merge"},{"ty":"fl","c":{"k":[0.82,0.84,0.88,1]},"o":{"k":100},"nm":"Fill 1","mn":"ADBE Vector Graphic - Fill"}],"ip":0,"op":44.0000017921567,"st":-107.000004358199,"bm":0,"sr":1}]},{"id":"comp_9","layers":[{"ddd":0,"ind":0,"ty":4,"nm":"pie_stroke_center_ball","ks":{"o":{"k":[{"i":{"x":[0.833],"y":[0.833]},"o":{"x":[0.167],"y":[0.167]},"n":["0p833_0p833_0p167_0p167"],"t":3,"s":[50],"e":[0]},{"t":5.00000020365417}]},"r":{"k":0},"p":{"k":[512,512,0]},"a":{"k":[0,0,0]},"s":{"k":[100,100,100]}},"ao":0,"shapes":[{"ty":"gr","it":[{"ty":"rc","d":1,"s":{"k":[3.022,10]},"p":{"k":[0,0]},"r":{"k":7},"nm":"Rectangle Path 1","mn":"ADBE Vector Shape - Rect"},{"ty":"tr","p":{"k":[{"i":{"x":0.667,"y":1},"o":{"x":0.333,"y":0},"n":"0p667_1_0p333_0","t":0,"s":[-7.573,-0.25],"e":[-10.073,-0.25],"to":[-0.41666665673256,0],"ti":[0.83333331346512,0]},{"i":{"x":0.667,"y":1},"o":{"x":0.333,"y":0},"n":"0p667_1_0p333_0","t":2.5,"s":[-10.073,-0.25],"e":[-12.573,-0.25],"to":[-0.83333331346512,0],"ti":[0.41666665673256,0]},{"t":5.00000020365417}],"ix":2},"a":{"k":[0,0],"ix":1},"s":{"k":[100,100],"ix":3},"r":{"k":90,"ix":6},"o":{"k":0,"ix":7},"sk":{"k":0,"ix":4},"sa":{"k":0,"ix":5},"nm":"Transform"}],"nm":"Rectangle 4","np":1,"mn":"ADBE Vector Group"},{"ty":"gr","it":[{"ty":"rc","d":1,"s":{"k":[3.022,10]},"p":{"k":[0,0]},"r":{"k":7},"nm":"Rectangle Path 1","mn":"ADBE Vector Shape - Rect"},{"ty":"tr","p":{"k":[{"i":{"x":0.667,"y":1},"o":{"x":0.333,"y":0},"n":"0p667_1_0p333_0","t":0,"s":[7.427,-0.75],"e":[9.927,-0.75],"to":[0.41666665673256,0],"ti":[-0.83333331346512,0]},{"i":{"x":0.667,"y":1},"o":{"x":0.333,"y":0},"n":"0p667_1_0p333_0","t":2.5,"s":[9.927,-0.75],"e":[12.427,-0.75],"to":[0.83333331346512,0],"ti":[-0.41666665673256,0]},{"t":5.00000020365417}],"ix":2},"a":{"k":[0,0],"ix":1},"s":{"k":[100,100],"ix":3},"r":{"k":90,"ix":6},"o":{"k":0,"ix":7},"sk":{"k":0,"ix":4},"sa":{"k":0,"ix":5},"nm":"Transform"}],"nm":"Rectangle 3","np":1,"mn":"ADBE Vector Group"},{"ty":"gr","it":[{"ty":"rc","d":1,"s":{"k":[3.022,10]},"p":{"k":[0,0]},"r":{"k":7},"nm":"Rectangle Path 1","mn":"ADBE Vector Shape - Rect"},{"ty":"tr","p":{"k":[{"i":{"x":0.667,"y":1},"o":{"x":0.333,"y":0},"n":"0p667_1_0p333_0","t":0,"s":[0.427,-6.75],"e":[0.427,-9.25],"to":[0,-0.41666665673256],"ti":[0,0.83333331346512]},{"i":{"x":0.667,"y":1},"o":{"x":0.333,"y":0},"n":"0p667_1_0p333_0","t":2.5,"s":[0.427,-9.25],"e":[0.427,-11.75],"to":[0,-0.83333331346512],"ti":[0,0.41666665673256]},{"t":5.00000020365417}],"ix":2},"a":{"k":[0,0],"ix":1},"s":{"k":[100,100],"ix":3},"r":{"k":1.025,"ix":6},"o":{"k":0,"ix":7},"sk":{"k":0,"ix":4},"sa":{"k":0,"ix":5},"nm":"Transform"}],"nm":"Rectangle 2","np":1,"mn":"ADBE Vector Group"},{"ty":"gr","it":[{"ty":"rc","d":1,"s":{"k":[3.022,10]},"p":{"k":[0,0]},"r":{"k":7},"nm":"Rectangle Path 1","mn":"ADBE Vector Shape - Rect"},{"ty":"tr","p":{"k":[{"i":{"x":0.667,"y":1},"o":{"x":0.333,"y":0},"n":"0p667_1_0p333_0","t":0,"s":[0.427,8.25],"e":[0.427,10.75],"to":[0,0.41666665673256],"ti":[0,-0.83333331346512]},{"i":{"x":0.667,"y":1},"o":{"x":0.333,"y":0},"n":"0p667_1_0p333_0","t":2.5,"s":[0.427,10.75],"e":[0.427,13.25],"to":[0,0.83333331346512],"ti":[0,-0.41666665673256]},{"t":5.00000020365417}],"ix":2},"a":{"k":[0,0],"ix":1},"s":{"k":[100,100],"ix":3},"r":{"k":1.025,"ix":6},"o":{"k":0,"ix":7},"sk":{"k":0,"ix":4},"sa":{"k":0,"ix":5},"nm":"Transform"}],"nm":"Rectangle 1","np":1,"mn":"ADBE Vector Group"},{"ty":"fl","c":{"k":[0,1,0.97,1]},"o":{"k":100},"nm":"Fill 1","mn":"ADBE Vector Graphic - Fill"}],"ip":0,"op":6.00000024438501,"st":-109.000004439661,"bm":0,"sr":1}]}],"layers":[{"ddd":0,"ind":0,"ty":0,"nm":"clock_wipe_on","refId":"comp_5","ks":{"o":{"k":100},"r":{"k":0},"p":{"k":[512,512,0]},"a":{"k":[512,512,0]},"s":{"k":[100,100,100]}},"ao":0,"w":1024,"h":1024,"ip":0,"op":147.000005987433,"st":0,"bm":0,"sr":1},{"ddd":0,"ind":1,"ty":0,"nm":"clock_wipe_off","refId":"comp_8","ks":{"o":{"k":100},"r":{"k":0},"p":{"k":[512,512,0]},"a":{"k":[512,512,0]},"s":{"k":[100,100,100]}},"ao":0,"w":1024,"h":1024,"ip":147.000005987433,"op":215.00000875713,"st":147.000005987433,"bm":0,"sr":1}],"v":"4.5.4","ddd":0,"ip":0,"op":242.000009856862,"fr":29.9700012207031,"w":1024,"h":1024}